suds/__init__.py
suds/builder.py
suds/cache.py
suds/client.py
suds/compat.py
suds/metrics.py
suds/options.py
suds/plugin.py
suds/properties.py
suds/reader.py
suds/resolver.py
suds/servicedefinition.py
suds/serviceproxy.py
suds/soaparray.py
suds/store.py
suds/sudsobject.py
suds/utils.py
suds/wsdl.py
suds/wsse.py
suds/__pycache__/__init__.cpython-37.opt-1.pyc
suds/__pycache__/builder.cpython-37.opt-1.pyc
suds/__pycache__/cache.cpython-37.opt-1.pyc
suds/__pycache__/client.cpython-37.opt-1.pyc
suds/__pycache__/compat.cpython-37.opt-1.pyc
suds/__pycache__/metrics.cpython-37.opt-1.pyc
suds/__pycache__/options.cpython-37.opt-1.pyc
suds/__pycache__/plugin.cpython-37.opt-1.pyc
suds/__pycache__/properties.cpython-37.opt-1.pyc
suds/__pycache__/reader.cpython-37.opt-1.pyc
suds/__pycache__/resolver.cpython-37.opt-1.pyc
suds/__pycache__/servicedefinition.cpython-37.opt-1.pyc
suds/__pycache__/serviceproxy.cpython-37.opt-1.pyc
suds/__pycache__/soaparray.cpython-37.opt-1.pyc
suds/__pycache__/store.cpython-37.opt-1.pyc
suds/__pycache__/sudsobject.cpython-37.opt-1.pyc
suds/__pycache__/utils.cpython-37.opt-1.pyc
suds/__pycache__/wsdl.cpython-37.opt-1.pyc
suds/__pycache__/wsse.cpython-37.opt-1.pyc
suds/bindings/__init__.py
suds/bindings/binding.py
suds/bindings/document.py
suds/bindings/multiref.py
suds/bindings/rpc.py
suds/bindings/__pycache__/__init__.cpython-37.opt-1.pyc
suds/bindings/__pycache__/binding.cpython-37.opt-1.pyc
suds/bindings/__pycache__/document.cpython-37.opt-1.pyc
suds/bindings/__pycache__/multiref.cpython-37.opt-1.pyc
suds/bindings/__pycache__/rpc.cpython-37.opt-1.pyc
suds/mx/__init__.py
suds/mx/appender.py
suds/mx/basic.py
suds/mx/core.py
suds/mx/encoded.py
suds/mx/literal.py
suds/mx/typer.py
suds/mx/__pycache__/__init__.cpython-37.opt-1.pyc
suds/mx/__pycache__/appender.cpython-37.opt-1.pyc
suds/mx/__pycache__/basic.cpython-37.opt-1.pyc
suds/mx/__pycache__/core.cpython-37.opt-1.pyc
suds/mx/__pycache__/encoded.cpython-37.opt-1.pyc
suds_py3-1.3.4.0.dist-info/LICENSE
suds_py3-1.3.4.0.dist-info/METADATA
suds_py3-1.3.4.0.dist-info/WHEEL
suds_py3-1.3.4.0.dist-info/top_level.txt
suds_py3-1.3.4.0.dist-info/RECORD
